sts_select/__init__.py
sts_select/gensim.py
sts_select/mrmr.py
sts_select/scoring.py
sts_select/target_sel.py
sts_select-0.0.1.dist-info/METADATA
sts_select-0.0.1.dist-info/WHEEL
sts_select-0.0.1.dist-info/licenses/LICENSE
sts_select-0.0.1.dist-info/RECORD
