Metadata-Version: 2.1
Name: sts-select
Version: 0.0.1
Summary: Feature selection tools based on semantic textual similarity (STS) scores.
Project-URL: Homepage, https://github.com/bcwarner/sts-select
Author-email: Benjamin Warner <b.c.warner@wustl.edu>, Ziqi Xu <ziqixu@wustl.edu>
License-File: LICENSE
Classifier: Intended Audience :: Science/Research
Classifier: License :: OSI Approved :: MIT License
Classifier: Programming Language :: Python :: 3.7
Classifier: Topic :: Scientific/Engineering :: Artificial Intelligence
Requires-Python: >=3.7
Provides-Extra: models
Requires-Dist: gensim>=4.0.0; extra == 'models'
Requires-Dist: sentence-transformers>=2.0.0; extra == 'models'
